README.md
setup.py
smartlogging/__init__.py
smartlogging/db.py
smartlogging/discord.py
smartlogging/logger.py
smartlogging/message.py
smartlogging/version.py
smartlogging.egg-info/PKG-INFO
smartlogging.egg-info/SOURCES.txt
smartlogging.egg-info/dependency_links.txt
smartlogging.egg-info/not-zip-safe
smartlogging.egg-info/requires.txt
smartlogging.egg-info/top_level.txt