Metadata-Version: 2.1
Name: smartlogging
Version: 0.0.3
Summary: Easy smart logging for you python project
Home-page: https://github.com/blue-walkers/smart-logger
Author: Maxwell Flitton and Florentin Hortet
Author-email: maxwellflitton@gmail.com
License: UNKNOWN
Platform: UNKNOWN
Classifier: Programming Language :: Python :: 3
Classifier: License :: OSI Approved :: MIT License
Classifier: Operating System :: OS Independent
Classifier: Development Status :: 1 - Planning
Classifier: Topic :: Scientific/Engineering :: Information Analysis
Classifier: Topic :: Software Development :: Build Tools
